{
  "out": "test_credit.mp4",
  "w": 1080, "h": 1920, "fps": 20, "dur": 24.0,
  "brand": ["เงินเดือนสมองทอง", "ไม่ขายฝัน"],
  "disclosure": "เนื้อหาเพื่อการศึกษา · ไม่ใช่คำแนะนำเฉพาะบุคคล · มีลิงก์พันธมิตร · ผลิตด้วย AI",
  "scenes": [
    {"t0": 0.0,  "t1": 4.6,  "k": "มนุษย์เงินเดือนหลายคนเจอ",     "h": ["เงินเดือนก็ถึงเกณฑ์", "[g]แต่บัตรใบแรก…ไม่ผ่าน?[/g]"], "s": null},
    {"t0": 4.6,  "t1": 9.6,  "k": "เพราะธนาคารไม่ได้ดูแค่รายได้", "h": ["เขาดู [g]ประวัติการจ่าย[/g]", "ที่คุณยังไม่มี"], "s": null},
    {"t0": 9.6,  "t1": 15.0, "k": "จุดที่หลายคนเข้าใจผิด",        "h": ["ไม่เคยมีหนี้", "= เครดิตบูโร [g]ว่างเปล่า[/g]"], "s": "ธนาคารเลยยังไม่รู้จักนิสัยการเงินของคุณ"},
    {"t0": 15.0, "t1": 20.0, "k": "ทางออกแบบไม่ต้องรีบ",          "h": ["เริ่มจากผลิตภัณฑ์ที่", "[g]เงื่อนไขผ่อนปรนกว่า[/g]"], "s": "ใช้ให้ตรงเวลา ค่อย ๆ สร้างประวัติให้ระบบเห็น"},
    {"t0": 20.0, "t1": 24.0, "k": "อยากเทียบตัวเลือกแบบไม่ขายฝัน?", "h": ["ลิงก์อยู่ใน", "[g]โปรไฟล์[/g]"], "s": null, "disc": true}
  ]
}
